Workbook

Sheet 🏠 Dashboard
A1: 🎓 SHOVON — Personal Academic & Life Manager
A2: ✦ University · Attendance · Study · Tasks · Finance · CGPA ✦
A3: Last Updated: 21 May 2026, 12:29 AM
A5: 📚 Total Courses | D5: 🎯 Attendance % | G5: ✅ Done Study % | J5: 💰 Total Expense | M5: ⭐ Current CGPA | P5: 📅 Pending Tasks
A6: =COUNTA('📋 Courses'!B5:B30) | D6: ='📊 Attendance'!S5 | G6: ='📖 Study Tracker'!L5 | J6: =SUM('💸 Expenses'!E5:E200) | M6: ='🏆 CGPA'!H5 | P6: =COUNTIF('📝 Tasks'!F5:F200,"Pending")
A10: 📌 Quick Navigation & Module Status
A12: 📋 Courses | F12: Configure all courses & semester info
A13: 📊 Attendance | F13: Mark & track class attendance
A14: 📖 Study Tracker | F14: Monitor study progress per course
A15: 📝 Tasks | F15: Daily task & routine manager
A16: 💸 Expenses | F16: Daily buy & expense tracker
A17: 💰 Money Manager | F17: Fund accounts & transactions
A18: 🏆 CGPA | F18: Marks, GPA & CGPA calculation
A19: 📅 Calendar | F19: Attendance calendar view
A20: 📑 Fee Manager | F20: Semester registration fees

Sheet 📋 Courses
A1: 📋 COURSE & SEMESTER CONFIGURATION
A2: Configure all courses, credits, instructors and semester details
A3: 🔵 Active Semester: | E3: 1st Semester
A4: # | B4: Semester | C4: Course Code | D4: Course Title | E4: Instructor | F4: Credit Hours | G4: Mid Marks | H4: Final Marks | I4: Assignment | J4: Lab | K4: Attendance Marks | L4: Total Marks | M4: Grade | N4: Status | O4: Start Date | P4: End Date | Q4: Notes
A5: 1 | B5: 1st Semester | C5: CSE101 | D5: Introduction to Programming | E5: Dr. Rahman | F5: 3 | G5: 25 | H5: 40 | I5: 10 | J5: 0 | K5: 10 | L5: =SUM(G5:K5) | M5: =IF(L5>=80,"A+",IF(L5>=75,"A",IF(L5>=70,"A-",IF(L5>=65,"B+",IF(L5>=60,"B",IF(L5>=55,"B-",IF(L5>=50,"C+",IF(L5>=45,"C",IF(L5>=40,"D","F"))))))))) | N5: Active
A6: 2 | B6: 1st Semester | C6: MATH101 | D6: Calculus I | E6: Prof. Khan | F6: 3 | G6: 25 | H6: 40 | I6: 10 | J6: 0 | K6: 10 | L6: =SUM(G6:K6) | M6: =IF(L6>=80,"A+",IF(L6>=75,"A",IF(L6>=70,"A-",IF(L6>=65,"B+",IF(L6>=60,"B",IF(L6>=55,"B-",IF(L6>=50,"C+",IF(L6>=45,"C",IF(L6>=40,"D","F"))))))))) | N6: Active
A7: 3 | B7: 1st Semester | C7: PHY101 | D7: Physics I | E7: Dr. Ahmed | F7: 3 | G7: 25 | H7: 40 | I7: 10 | J7: 5 | K7: 10 | L7: =SUM(G7:K7) | M7: =IF(L7>=80,"A+",IF(L7>=75,"A",IF(L7>=70,"A-",IF(L7>=65,"B+",IF(L7>=60,"B",IF(L7>=55,"B-",IF(L7>=50,"C+",IF(L7>=45,"C",IF(L7>=40,"D","F"))))))))) | N7: Active
A8: 4 | B8: 1st Semester | C8: ENG101 | D8: English Communication | E8: Ms. Fatema | F8: 2 | G8: 25 | H8: 40 | I8: 10 | J8: 0 | K8: 10 | L8: =SUM(G8:K8) | M8: =IF(L8>=80,"A+",IF(L8>=75,"A",IF(L8>=70,"A-",IF(L8>=65,"B+",IF(L8>=60,"B",IF(L8>=55,"B-",IF(L8>=50,"C+",IF(L8>=45,"C",IF(L8>=40,"D","F"))))))))) | N8: Active
A9: 5 | B9: 2nd Semester | C9: CSE201 | D9: Data Structures | E9: Dr. Islam | F9: 3 | G9: 25 | H9: 40 | I9: 10 | J9: 0 | K9: 10 | L9: =SUM(G9:K9) | M9: =IF(L9>=80,"A+",IF(L9>=75,"A",IF(L9>=70,"A-",IF(L9>=65,"B+",IF(L9>=60,"B",IF(L9>=55,"B-",IF(L9>=50,"C+",IF(L9>=45,"C",IF(L9>=40,"D","F"))))))))) | N9: Active
A10: 6 | B10: 2nd Semester | C10: MATH201 | D10: Calculus II | E10: Prof. Hossain | F10: 3 | G10: 25 | H10: 40 | I10: 10 | J10: 0 | K10: 10 | L10: =SUM(G10:K10) | M10: =IF(L10>=80,"A+",IF(L10>=75,"A",IF(L10>=70,"A-",IF(L10>=65,"B+",IF(L10>=60,"B",IF(L10>=55,"B-",IF(L10>=50,"C+",IF(L10>=45,"C",IF(L10>=40,"D","F"))))))))) | N10: Active
A12: TOTALS & AVERAGES | L12: =AVERAGE(L5:L10)
A14: 📌 Total Credits Registered: | E14: =SUM(F5:F10)

Sheet 📊 Attendance
A1: 📊 ATTENDANCE TRACKER
A2: Mark attendance, track presence/absence, monitor attendance % per course
A3: 📅 Filter Semester: | D3: All Semesters
A4: # | B4: Date | C4: Day | D4: Semester | E4: Course Code | F4: Course Title | G4: Instructor | H4: Class Time | I4: Status | J4: Extra Class | K4: Online/Offline | L4: Topic Covered | M4: Signature Count | N4: Notes | O4: Week No | P4: Month | Q4: Year | R4: Running Present | S4: Running Absent | T4: Running Total | U4: Att. % | V4: Remarks
A5: 1 | B5: 05-01-2026 | C5: Mon | D5: 1st Semester | E5: CSE101 | F5: Introduction to Programming | G5: Dr. Rahman | H5: 08:00 AM - 09:30 AM | I5: Present | J5: No | K5: Offline | L5: Variables & Data Types | M5: 2 | O5: =WEEKNUM(B5) | P5: =TEXT(B5,"mmmm") | Q5: =YEAR(B5) | R5: =COUNTIFS($I$5:I5,"Present",$E$5:E5,E5) | S5: =IFERROR(COUNTIF(I5:I200,"Present")/COUNTA(I5:I200),0) | T5: =R5+S5 | U5: =IF(T5=0,0,R5/T5) | V5: =IF(U5>=0.75,"✅ Good",IF(U5>=0.60,"⚠️ Warning","❌ Low"))
A6: 2 | B6: 05-01-2026 | C6: Mon | D6: 1st Semester | E6: MATH101 | F6: Calculus I | G6: Prof. Khan | H6: 10:00 AM - 11:30 AM | I6: Present | J6: No | K6: Offline | L6: Limits | M6: 2 | O6: =WEEKNUM(B6) | P6: =TEXT(B6,"mmmm") | Q6: =YEAR(B6) | R6: =COUNTIFS($I$5:I6,"Present",$E$5:E6,E6) | S6: =COUNTIFS($I$5:I6,"Absent",$E$5:E6,E6) | T6: =R6+S6 | U6: =IF(T6=0,0,R6/T6) | V6: =IF(U6>=0.75,"✅ Good",IF(U6>=0.60,"⚠️ Warning","❌ Low"))
A7: 3 | B7: 05-01-2026 | C7: Mon | D7: 1st Semester | E7: PHY101 | F7: Physics I | G7: Dr. Ahmed | H7: 12:00 PM - 01:30 PM | I7: Absent | J7: No | K7: Offline | L7: Motion | M7: 0 | O7: =WEEKNUM(B7) | P7: =TEXT(B7,"mmmm") | Q7: =YEAR(B7) | R7: =COUNTIFS($I$5:I7,"Present",$E$5:E7,E7) | S7: =COUNTIFS($I$5:I7,"Absent",$E$5:E7,E7) | T7: =R7+S7 | U7: =IF(T7=0,0,R7/T7) | V7: =IF(U7>=0.75,"✅ Good",IF(U7>=0.60,"⚠️ Warning","❌ Low"))
A8: 4 | B8: 07-01-2026 | C8: Wed | D8: 1st Semester | E8: CSE101 | F8: Introduction to Programming | G8: Dr. Rahman | H8: 08:00 AM - 09:30 AM | I8: Present | J8: No | K8: Online | L8: Control Flow | M8: 2 | O8: =WEEKNUM(B8) | P8: =TEXT(B8,"mmmm") | Q8: =YEAR(B8) | R8: =COUNTIFS($I$5:I8,"Present",$E$5:E8,E8) | S8: =COUNTIFS($I$5:I8,"Absent",$E$5:E8,E8) | T8: =R8+S8 | U8: =IF(T8=0,0,R8/T8) | V8: =IF(U8>=0.75,"✅ Good",IF(U8>=0.60,"⚠️ Warning","❌ Low"))
A9: 5 | B9: 07-01-2026 | C9: Wed | D9: 1st Semester | E9: MATH101 | F9: Calculus I | G9: Prof. Khan | H9: 10:00 AM - 11:30 AM | I9: Present | J9: Yes | K9: Offline | L9: Derivatives | M9: 2 | O9: =WEEKNUM(B9) | P9: =TEXT(B9,"mmmm") | Q9: =YEAR(B9) | R9: =COUNTIFS($I$5:I9,"Present",$E$5:E9,E9) | S9: =COUNTIFS($I$5:I9,"Absent",$E$5:E9,E9) | T9: =R9+S9 | U9: =IF(T9=0,0,R9/T9) | V9: =IF(U9>=0.75,"✅ Good",IF(U9>=0.60,"⚠️ Warning","❌ Low"))
A10: 6 | B10: 02-02-2026 | C10: Mon | D10: 2nd Semester | E10: CSE201 | F10: Data Structures | G10: Dr. Islam | H10: 09:00 AM - 10:30 AM | I10: Present | J10: No | K10: Offline | L10: Arrays | M10: 2 | O10: =WEEKNUM(B10) | P10: =TEXT(B10,"mmmm") | Q10: =YEAR(B10) | R10: =COUNTIFS($I$5:I10,"Present",$E$5:E10,E10) | S10: =COUNTIFS($I$5:I10,"Absent",$E$5:E10,E10) | T10: =R10+S10 | U10: =IF(T10=0,0,R10/T10) | V10: =IF(U10>=0.75,"✅ Good",IF(U10>=0.60,"⚠️ Warning","❌ Low"))
A11: 7 | B11: 04-02-2026 | C11: Wed | D11: 2nd Semester | E11: CSE201 | F11: Data Structures | G11: Dr. Islam | H11: 09:00 AM - 10:30 AM | I11: Present | J11: No | K11: Offline | L11: Linked Lists | M11: 2 | O11: =WEEKNUM(B11) | P11: =TEXT(B11,"mmmm") | Q11: =YEAR(B11) | R11: =COUNTIFS($I$5:I11,"Present",$E$5:E11,E11) | S11: =COUNTIFS($I$5:I11,"Absent",$E$5:E11,E11) | T11: =R11+S11 | U11: =IF(T11=0,0,R11/T11) | V11: =IF(U11>=0.75,"✅ Good",IF(U11>=0.60,"⚠️ Warning","❌ Low"))
A12: 8 | B12: 04-02-2026 | C12: Wed | D12: 2nd Semester | E12: MATH201 | F12: Calculus II | G12: Prof. Hossain | H12: 11:00 AM - 12:30 PM | I12: Absent | J12: No | K12: Offline | L12: Integration | M12: 0 | O12: =WEEKNUM(B12) | P12: =TEXT(B12,"mmmm") | Q12: =YEAR(B12) | R12: =COUNTIFS($I$5:I12,"Present",$E$5:E12,E12) | S12: =COUNTIFS($I$5:I12,"Absent",$E$5:E12,E12) | T12: =R12+S12 | U12: =IF(T12=0,0,R12/T12) | V12: =IF(U12>=0.75,"✅ Good",IF(U12>=0.60,"⚠️ Warning","❌ Low"))
A210: 📊 COURSE-WISE ATTENDANCE SUMMARY
A211: Course Code | B211: Course Title | C211: Total Classes | D211: Present | E211: Absent | F211: Extra | G211: Attendance % | H211: Status
A212: CSE101 | B212: Introduction to Programming | C212: =COUNTIF($E$5:$E$200,A212) | D212: =COUNTIFS($E$5:$E$200,A212,$I$5:$I$200,"Present") | E212: =COUNTIFS($E$5:$E$200,A212,$I$5:$I$200,"Absent") | F212: =COUNTIFS($E$5:$E$200,A212,$J$5:$J$200,"Yes") | G212: =IF(C212=0,0,D212/C212) | H212: =IF(G212>=0.75,"✅ Good",IF(G212>=0.60,"⚠️ Warning","❌ Critical"))
A213: MATH101 | B213: Calculus I | C213: =COUNTIF($E$5:$E$200,A213) | D213: =COUNTIFS($E$5:$E$200,A213,$I$5:$I$200,"Present") | E213: =COUNTIFS($E$5:$E$200,A213,$I$5:$I$200,"Absent") | F213: =COUNTIFS($E$5:$E$200,A213,$J$5:$J$200,"Yes") | G213: =IF(C213=0,0,D213/C213) | H213: =IF(G213>=0.75,"✅ Good",IF(G213>=0.60,"⚠️ Warning","❌ Critical"))
A214: PHY101 | B214: Physics I | C214: =COUNTIF($E$5:$E$200,A214) | D214: =COUNTIFS($E$5:$E$200,A214,$I$5:$I$200,"Present") | E214: =COUNTIFS($E$5:$E$200,A214,$I$5:$I$200,"Absent") | F214: =COUNTIFS($E$5:$E$200,A214,$J$5:$J$200,"Yes") | G214: =IF(C214=0,0,D214/C214) | H214: =IF(G214>=0.75,"✅ Good",IF(G214>=0.60,"⚠️ Warning","❌ Critical"))
A215: CSE201 | B215: Data Structures | C215: =COUNTIF($E$5:$E$200,A215) | D215: =COUNTIFS($E$5:$E$200,A215,$I$5:$I$200,"Present") | E215: =COUNTIFS($E$5:$E$200,A215,$I$5:$I$200,"Absent") | F215: =COUNTIFS($E$5:$E$200,A215,$J$5:$J$200,"Yes") | G215: =IF(C215=0,0,D215/C215) | H215: =IF(G215>=0.75,"✅ Good",IF(G215>=0.60,"⚠️ Warning","❌ Critical"))
A216: MATH201 | B216: Calculus II | C216: =COUNTIF($E$5:$E$200,A216) | D216: =COUNTIFS($E$5:$E$200,A216,$I$5:$I$200,"Present") | E216: =COUNTIFS($E$5:$E$200,A216,$I$5:$I$200,"Absent") | F216: =COUNTIFS($E$5:$E$200,A216,$J$5:$J$200,"Yes") | G216: =IF(C216=0,0,D216/C216) | H216: =IF(G216>=0.75,"✅ Good",IF(G216>=0.60,"⚠️ Warning","❌ Critical"))

Sheet 📖 Study Tracker
A1: 📖 DONE STUDY TRACKER
A2: Track which classes you have studied. Mark sessions as Done or Pending.
A4: # | B4: Semester | C4: Course Code | D4: Course Title | E4: Class Date | F4: Day | G4: Topic Covered | H4: Study Status | I4: Study Date | J4: Time Spent (hrs) | K4: Notes | L4: Difficulty | M4: Priority | N4: % Complete | O4: Remarks
A5: 1 | B5: 1st Semester | C5: CSE101 | D5: Introduction to Programming | E5: 2026-01-05 | F5: Mon | G5: Variables & Data Types | H5: Done | I5: 2026-01-06 | J5: 2.5 | L5: =IFERROR(COUNTIF(H5:H100,"Done")/COUNTA(H5:H100),0) | M5: Medium | N5: =IF(H5="Done",1,0) | O5: =IF(H5="Done","✅ Complete","⏳ Pending")
A6: 2 | B6: 1st Semester | C6: MATH101 | D6: Calculus I | E6: 2026-01-05 | F6: Mon | G6: Limits | H6: Done | I6: 2026-01-07 | J6: 3 | L6: Medium | M6: Medium | N6: =IF(H6="Done",1,0) | O6: =IF(H6="Done","✅ Complete","⏳ Pending")
A7: 3 | B7: 1st Semester | C7: PHY101 | D7: Physics I | E7: 2026-01-05 | F7: Mon | G7: Motion | H7: Pending | L7: Hard | M7: High | N7: =IF(H7="Done",1,0) | O7: =IF(H7="Done","✅ Complete","⏳ Pending")
A8: 4 | B8: 1st Semester | C8: CSE101 | D8: Introduction to Programming | E8: 2026-01-07 | F8: Wed | G8: Control Flow | H8: Done | I8: 2026-01-08 | J8: 1.5 | L8: Easy | M8: Medium | N8: =IF(H8="Done",1,0) | O8: =IF(H8="Done","✅ Complete","⏳ Pending")
A9: 5 | B9: 1st Semester | C9: MATH101 | D9: Calculus I | E9: 2026-01-07 | F9: Wed | G9: Derivatives | H9: Pending | L9: Hard | M9: High | N9: =IF(H9="Done",1,0) | O9: =IF(H9="Done","✅ Complete","⏳ Pending")
A10: 6 | B10: 2nd Semester | C10: CSE201 | D10: Data Structures | E10: 2026-02-02 | F10: Mon | G10: Arrays | H10: Done | I10: 2026-02-03 | J10: 2 | L10: Medium | M10: Medium | N10: =IF(H10="Done",1,0) | O10: =IF(H10="Done","✅ Complete","⏳ Pending")
A11: 7 | B11: 2nd Semester | C11: CSE201 | D11: Data Structures | E11: 2026-02-04 | F11: Wed | G11: Linked Lists | H11: Pending | L11: Hard | M11: High | N11: =IF(H11="Done",1,0) | O11: =IF(H11="Done","✅ Complete","⏳ Pending")
A12: 8 | B12: 2nd Semester | C12: MATH201 | D12: Calculus II | E12: 2026-02-04 | F12: Wed | G12: Integration | H12: Pending | L12: Hard | M12: High | N12: =IF(H12="Done",1,0) | O12: =IF(H12="Done","✅ Complete","⏳ Pending")
A15: 📊 COURSE-WISE STUDY PROGRESS
A16: Course | B16: Total Sessions | C16: Done | D16: Pending | E16: Progress % | F16: Time Spent
A17: CSE101 | B17: =COUNTIF($C$5:$C$100,A17) | C17: =COUNTIFS($C$5:$C$100,A17,$H$5:$H$100,"Done") | D17: =COUNTIFS($C$5:$C$100,A17,$H$5:$H$100,"Pending") | E17: =IFERROR(C17/B17,0) | F17: =SUMIF($C$5:$C$100,A17,$J$5:$J$100)&" hrs"
A18: MATH101 | B18: =COUNTIF($C$5:$C$100,A18) | C18: =COUNTIFS($C$5:$C$100,A18,$H$5:$H$100,"Done") | D18: =COUNTIFS($C$5:$C$100,A18,$H$5:$H$100,"Pending") | E18: =IFERROR(C18/B18,0) | F18: =SUMIF($C$5:$C$100,A18,$J$5:$J$100)&" hrs"
A19: PHY101 | B19: =COUNTIF($C$5:$C$100,A19) | C19: =COUNTIFS($C$5:$C$100,A19,$H$5:$H$100,"Done") | D19: =COUNTIFS($C$5:$C$100,A19,$H$5:$H$100,"Pending") | E19: =IFERROR(C19/B19,0) | F19: =SUMIF($C$5:$C$100,A19,$J$5:$J$100)&" hrs"
A20: CSE201 | B20: =COUNTIF($C$5:$C$100,A20) | C20: =COUNTIFS($C$5:$C$100,A20,$H$5:$H$100,"Done") | D20: =COUNTIFS($C$5:$C$100,A20,$H$5:$H$100,"Pending") | E20: =IFERROR(C20/B20,0) | F20: =SUMIF($C$5:$C$100,A20,$J$5:$J$100)&" hrs"
A21: MATH201 | B21: =COUNTIF($C$5:$C$100,A21) | C21: =COUNTIFS($C$5:$C$100,A21,$H$5:$H$100,"Done") | D21: =COUNTIFS($C$5:$C$100,A21,$H$5:$H$100,"Pending") | E21: =IFERROR(C21/B21,0) | F21: =SUMIF($C$5:$C$100,A21,$J$5:$J$100)&" hrs"

Sheet 📝 Tasks
A1: 📝 DAILY TASK & ROUTINE MANAGER
A2: Add, update and track all daily tasks with priority, deadline and status
A4: # | B4: Task Name | C4: Category | D4: Description | E4: Date | F4: Day | G4: Status | H4: Priority | I4: Start Time | J4: End Time | K4: Deadline | L4: Days Left | M4: Completed On | N4: Notes
A5: 1 | B5: Complete Assignment 3 | C5: Study | D5: Submit DSA assignment | E5: 2026-05-22 | F5: Fri | G5: Pending | H5: High | I5: 09:00 AM | J5: 11:00 AM | K5: 2026-05-22 | L5: =IFERROR(DATEVALUE(K5)-TODAY(),"—")
A6: 2 | B6: Buy Stationery | C6: Shopping | D6: Buy pens, notebook | E6: 2026-05-20 | F6: Wed | G6: Completed | H6: Low | I6: 04:00 PM | J6: 05:00 PM | K6: 2026-05-20 | L6: =IFERROR(DATEVALUE(K6)-TODAY(),"—") | M6: 2026-05-20
A7: 3 | B7: Study Calculus | C7: Study | D7: Chapter 5 exercises | E7: 2026-05-20 | F7: Wed | G7: Pending | H7: High | I7: 08:00 PM | J7: 10:00 PM | K7: 2026-05-21 | L7: =IFERROR(DATEVALUE(K7)-TODAY(),"—")
A8: 4 | B8: Exercise | C8: Personal | D8: Morning workout | E8: 2026-05-21 | F8: Thu | G8: Incomplete | H8: Medium | I8: 06:00 AM | J8: 07:00 AM | K8: 2026-05-21 | L8: =IFERROR(DATEVALUE(K8)-TODAY(),"—")
A9: 5 | B9: Lab Report | C9: University | D9: Physics lab report | E9: 2026-05-23 | F9: Sat | G9: Pending | H9: High | I9: 02:00 PM | J9: 04:00 PM | K9: 2026-05-24 | L9: =IFERROR(DATEVALUE(K9)-TODAY(),"—")
A10: 6 | B10: Read Novel | C10: Personal | D10: Read 30 pages | E10: 2026-05-20 | F10: Wed | G10: Completed | H10: Low | I10: 09:00 PM | J10: 10:00 PM | K10: 2026-05-20 | L10: =IFERROR(DATEVALUE(K10)-TODAY(),"—") | M10: 2026-05-20
A210: 📊 TASK SUMMARY
A211: Pending | C211: Completed | E211: Incomplete
A212: =COUNTIF(G5:G200,"Pending") | C212: =COUNTIF(G5:G200,"Completed") | E212: =COUNTIF(G5:G200,"Incomplete")

Sheet 💸 Expenses
A1: 💸 DAILY BUY & EXPENSE TRACKER
A2: Track all purchases, expenses and payment status
A4: # | B4: Date | C4: Day | D4: Item Name | E4: Amount (৳) | F4: Category | G4: Quantity | H4: Total (৳) | I4: Payment Status | J4: Payment Method | K4: Notes | L4: Month
A5: 1 | B5: 2026-05-18 | C5: Mon | D5: Rice 5kg | E5: 280 | F5: Food | G5: 1 | H5: =E5*G5 | I5: Received | J5: Cash | L5: =TEXT(B5,"mmmm")
A6: 2 | B6: 2026-05-18 | C6: Mon | D6: Vegetables | E6: 120 | F6: Food | G6: 1 | H6: =E6*G6 | I6: Received | J6: Cash | L6: =TEXT(B6,"mmmm")
A7: 3 | B7: 2026-05-19 | C7: Tue | D7: Bus Fare | E7: 40 | F7: Transport | G7: 2 | H7: =E7*G7 | I7: Received | J7: Cash | L7: =TEXT(B7,"mmmm")
A8: 4 | B8: 2026-05-19 | C8: Tue | D8: Notebook | E8: 60 | F8: Stationery | G8: 2 | H8: =E8*G8 | I8: Pending | J8: Cash | L8: =TEXT(B8,"mmmm")
A9: 5 | B9: 2026-05-20 | C9: Wed | D9: Lunch | E9: 80 | F9: Food | G9: 1 | H9: =E9*G9 | I9: Received | J9: bKash | L9: =TEXT(B9,"mmmm")
A10: 6 | B10: 2026-05-20 | C10: Wed | D10: Mobile Recharge | E10: 100 | F10: Personal | G10: 1 | H10: =E10*G10 | I10: Pending | J10: Nagad | L10: =TEXT(B10,"mmmm")
A11: 7 | B11: 2026-05-20 | C11: Wed | D11: Pen Set | E11: 45 | F11: Stationery | G11: 1 | H11: =E11*G11 | I11: Received | J11: Cash | L11: =TEXT(B11,"mmmm")
A12: 8 | B12: 2026-05-20 | C12: Wed | D12: Medicine | E12: 150 | F12: Health | G12: 1 | H12: =E12*G12 | I12: Pending | J12: Cash | L12: =TEXT(B12,"mmmm")
A14: TOTAL EXPENSE | H14: =SUM(H5:H12)
A16: 📊 CATEGORY-WISE EXPENSE SUMMARY
A17: Food | B17: =SUMIF($F$5:$F$200,A17,$H$5:$H$200)
A18: Transport | B18: =SUMIF($F$5:$F$200,A18,$H$5:$H$200)
A19: Stationery | B19: =SUMIF($F$5:$F$200,A19,$H$5:$H$200)
A20: Personal | B20: =SUMIF($F$5:$F$200,A20,$H$5:$H$200)
A21: University | B21: =SUMIF($F$5:$F$200,A21,$H$5:$H$200)
A22: Health | B22: =SUMIF($F$5:$F$200,A22,$H$5:$H$200)
A23: Shopping | B23: =SUMIF($F$5:$F$200,A23,$H$5:$H$200)
A24: Entertainment | B24: =SUMIF($F$5:$F$200,A24,$H$5:$H$200)
A25: Other | B25: =SUMIF($F$5:$F$200,A25,$H$5:$H$200)

Sheet 💰 Money Manager
A1: 💰 FUND & MONEY MANAGER
A2: Manage all your accounts: Bank, bKash, Nagad, Rocket, Cash
A4: Account Name | B4: Account Type | C4: Account No | D4: Opening Balance (৳) | E4: Total Deposit (৳) | F4: Total Withdraw (৳) | G4: Current Balance (৳) | H4: Status
A5: My bKash | B5: bKash | C5: 01XXXXXXXXX | D5: 500 | E5: =SUMIFS($I$15:$I$200,$G$15:$G$200,A5,$H$15:$H$200,"Deposit")+D5 | F5: =SUMIFS($I$15:$I$200,$G$15:$G$200,A5,$H$15:$H$200,"Withdraw") | G5: =E5-F5 | H5: Active
A6: My Bank | B6: Bank | C6: ACC-XXXXXXX | D6: 5000 | E6: =SUMIFS($I$15:$I$200,$G$15:$G$200,A6,$H$15:$H$200,"Deposit")+D6 | F6: =SUMIFS($I$15:$I$200,$G$15:$G$200,A6,$H$15:$H$200,"Withdraw") | G6: =E6-F6 | H6: Active
A7: Nagad | B7: Nagad | C7: 01XXXXXXXXX | D7: 200 | E7: =SUMIFS($I$15:$I$200,$G$15:$G$200,A7,$H$15:$H$200,"Deposit")+D7 | F7: =SUMIFS($I$15:$I$200,$G$15:$G$200,A7,$H$15:$H$200,"Withdraw") | G7: =E7-F7 | H7: Active
A8: Hand Cash | B8: Cash | C8: — | D8: 1000 | E8: =SUMIFS($I$15:$I$200,$G$15:$G$200,A8,$H$15:$H$200,"Deposit")+D8 | F8: =SUMIFS($I$15:$I$200,$G$15:$G$200,A8,$H$15:$H$200,"Withdraw") | G8: =E8-F8 | H8: Active
A10: 💰 TOTAL BALANCE (ALL ACCOUNTS) | G10: =SUM(G5:G8)
A13: 📋 TRANSACTION HISTORY
A14: # | B14: Date | C14: Day | D14: Time | E14: Description | F14: Category | G14: Account | H14: Type | I14: Amount (৳) | J14: Balance After (৳) | K14: Ref No | L14: Notes
A15: 1 | B15: 2026-05-18 | C15: Mon | D15: 10:30 AM | E15: Received from home | F15: Transfer | G15: My bKash | H15: Deposit | I15: 2000 | K15: TXN-1000
A16: 2 | B16: 2026-05-18 | C16: Mon | D16: 11:00 AM | E16: Bus fare | F16: Transport | G16: Hand Cash | H16: Withdraw | I16: 40 | K16: TXN-1001
A17: 3 | B17: 2026-05-19 | C17: Tue | D17: 09:00 AM | E17: Rice purchase | F17: Food | G17: Hand Cash | H17: Withdraw | I17: 280 | K17: TXN-1002
A18: 4 | B18: 2026-05-19 | C18: Tue | D18: 03:00 PM | E18: Mobile bill | F18: Personal | G18: My bKash | H18: Withdraw | I18: 100 | K18: TXN-1003
A19: 5 | B19: 2026-05-20 | C19: Wed | D19: 08:00 AM | E19: Pocket money | F19: Transfer | G19: Hand Cash | H19: Deposit | I19: 500 | K19: TXN-1004

Sheet 🏆 CGPA
A1: 🏆 CGPA & RESULT TRACKER
A2: Enter marks per course, GPA auto-calculated. CGPA updates automatically.
A4: Semester | B4: Course Code | C4: Course Title | D4: Credit | E4: Mid (30) | F4: Final (60) | G4: Assignment (5) | H4: Attendance (5) | I4: Total (100) | J4: GPA (4.0) | K4: Grade | L4: Grade Point | M4: Weighted Points | N4: Remarks
A5: 1st Semester | B5: CSE101 | C5: Introduction to Programming | D5: 3 | E5: 26 | F5: 52 | G5: 4 | H5: =IFERROR(SUM($M$5:$M$50)/SUM($D$5:$D$50),0) | I5: =E5+F5+G5+H5 | J5: =IF(I5>=80,4.0,IF(I5>=75,3.75,IF(I5>=70,3.5,IF(I5>=65,3.25,IF(I5>=60,3.0,IF(I5>=55,2.75,IF(I5>=50,2.5,IF(I5>=45,2.25,IF(I5>=40,2.0,0.0))))))))) | K5: =IF(I5>=80,"A+",IF(I5>=75,"A",IF(I5>=70,"A-",IF(I5>=65,"B+",IF(I5>=60,"B",IF(I5>=55,"B-",IF(I5>=50,"C+",IF(I5>=45,"C",IF(I5>=40,"D","F"))))))))) | L5: =J5 | M5: =D5*J5
A6: 1st Semester | B6: MATH101 | C6: Calculus I | D6: 3 | E6: 22 | F6: 48 | G6: 3 | H6: 5 | I6: =E6+F6+G6+H6 | J6: =IF(I6>=80,4.0,IF(I6>=75,3.75,IF(I6>=70,3.5,IF(I6>=65,3.25,IF(I6>=60,3.0,IF(I6>=55,2.75,IF(I6>=50,2.5,IF(I6>=45,2.25,IF(I6>=40,2.0,0.0))))))))) | K6: =IF(I6>=80,"A+",IF(I6>=75,"A",IF(I6>=70,"A-",IF(I6>=65,"B+",IF(I6>=60,"B",IF(I6>=55,"B-",IF(I6>=50,"C+",IF(I6>=45,"C",IF(I6>=40,"D","F"))))))))) | L6: =J6 | M6: =D6*J6
A7: 1st Semester | B7: PHY101 | C7: Physics I | D7: 3 | E7: 20 | F7: 40 | G7: 4 | H7: 4 | I7: =E7+F7+G7+H7 | J7: =IF(I7>=80,4.0,IF(I7>=75,3.75,IF(I7>=70,3.5,IF(I7>=65,3.25,IF(I7>=60,3.0,IF(I7>=55,2.75,IF(I7>=50,2.5,IF(I7>=45,2.25,IF(I7>=40,2.0,0.0))))))))) | K7: =IF(I7>=80,"A+",IF(I7>=75,"A",IF(I7>=70,"A-",IF(I7>=65,"B+",IF(I7>=60,"B",IF(I7>=55,"B-",IF(I7>=50,"C+",IF(I7>=45,"C",IF(I7>=40,"D","F"))))))))) | L7: =J7 | M7: =D7*J7
A8: 1st Semester | B8: ENG101 | C8: English Communication | D8: 2 | E8: 28 | F8: 55 | G8: 5 | H8: 5 | I8: =E8+F8+G8+H8 | J8: =IF(I8>=80,4.0,IF(I8>=75,3.75,IF(I8>=70,3.5,IF(I8>=65,3.25,IF(I8>=60,3.0,IF(I8>=55,2.75,IF(I8>=50,2.5,IF(I8>=45,2.25,IF(I8>=40,2.0,0.0))))))))) | K8: =IF(I8>=80,"A+",IF(I8>=75,"A",IF(I8>=70,"A-",IF(I8>=65,"B+",IF(I8>=60,"B",IF(I8>=55,"B-",IF(I8>=50,"C+",IF(I8>=45,"C",IF(I8>=40,"D","F"))))))))) | L8: =J8 | M8: =D8*J8
A9: 2nd Semester | B9: CSE201 | C9: Data Structures | D9: 3 | E9: 24 | F9: 50 | G9: 4 | H9: 5 | I9: =E9+F9+G9+H9 | J9: =IF(I9>=80,4.0,IF(I9>=75,3.75,IF(I9>=70,3.5,IF(I9>=65,3.25,IF(I9>=60,3.0,IF(I9>=55,2.75,IF(I9>=50,2.5,IF(I9>=45,2.25,IF(I9>=40,2.0,0.0))))))))) | K9: =IF(I9>=80,"A+",IF(I9>=75,"A",IF(I9>=70,"A-",IF(I9>=65,"B+",IF(I9>=60,"B",IF(I9>=55,"B-",IF(I9>=50,"C+",IF(I9>=45,"C",IF(I9>=40,"D","F"))))))))) | L9: =J9 | M9: =D9*J9
A10: 2nd Semester | B10: MATH201 | C10: Calculus II | D10: 3 | E10: 19 | F10: 42 | G10: 3 | H10: 4 | I10: =E10+F10+G10+H10 | J10: =IF(I10>=80,4.0,IF(I10>=75,3.75,IF(I10>=70,3.5,IF(I10>=65,3.25,IF(I10>=60,3.0,IF(I10>=55,2.75,IF(I10>=50,2.5,IF(I10>=45,2.25,IF(I10>=40,2.0,0.0))))))))) | K10: =IF(I10>=80,"A+",IF(I10>=75,"A",IF(I10>=70,"A-",IF(I10>=65,"B+",IF(I10>=60,"B",IF(I10>=55,"B-",IF(I10>=50,"C+",IF(I10>=45,"C",IF(I10>=40,"D","F"))))))))) | L10: =J10 | M10: =D10*J10
A13: 📊 SEMESTER WISE SGPA & CGPA
A14: Semester | B14: Total Credits | C14: Total Weighted Points | D14: SGPA | E14: Running CGPA | F14: Performance
A15: 1st Semester | B15: =SUMIF($A$5:$A$50,A15,$D$5:$D$50) | C15: =SUMIF($A$5:$A$50,A15,$M$5:$M$50) | D15: =IFERROR(C15/B15,0) | E15: =D15 | F15: =IF(E15>=3.75,"🌟 Excellent",IF(E15>=3.5,"⭐ Very Good",IF(E15>=3.0,"✅ Good",IF(E15>=2.5,"📘 Average","⚠️ Below Avg"))))
A16: 2nd Semester | B16: =SUMIF($A$5:$A$50,A16,$D$5:$D$50) | C16: =SUMIF($A$5:$A$50,A16,$M$5:$M$50) | D16: =IFERROR(C16/B16,0) | E16: =IFERROR(SUM($C$15:C16)/SUM($B$15:B16),0) | F16: =IF(E16>=3.75,"🌟 Excellent",IF(E16>=3.5,"⭐ Very Good",IF(E16>=3.0,"✅ Good",IF(E16>=2.5,"📘 Average","⚠️ Below Avg"))))

Sheet 📅 Calendar
A1: 📅 ATTENDANCE CALENDAR — MAY 2026
A3: Sun | B3: Mon | C3: Tue | D3: Wed | E3: Thu | F3: Fri | G3: Sat
E4: 1 | F4: 2 | G4: 3
A9: 4 | B9: 5 | C9: 6 | D9: 7 | E9: 8 | F9: 9 | G9: 10
B10: CSE101 | D10: CSE101
B11: MATH101 | D11: PHY101
A14: 11 | B14: 12 | C14: 13 | D14: 14 | E14: 15 | F14: 16 | G14: 17
B15: MATH101 | D15: CSE101
B16: CSE201 | D16: CSE201
A19: 18 | B19: 19 | C19: 20 | D19: 21 | E19: 22 | F19: 23 | G19: 24
B20: MATH101 | C20: CSE101 | D20: CSE201
C21: PHY101
A24: 25 | B24: 26 | C24: 27 | D24: 28 | E24: 29 | F24: 30 | G24: 31
B25: CSE101 | D25: CSE201
B26: MATH101
B27: PHY101
A30: 🟢 Green = Present 🔴 Red = Absent 🔵 Blue highlight = Today

Sheet 📑 Fee Manager
A1: 📑 REGISTRATION FEE MANAGER
A2: Track all semester registration fees, payment status and due amounts
A4: # | B4: Semester | C4: Fee Type | D4: Amount (৳) | E4: Due Date | F4: Payment Date | G4: Payment Status | H4: Payment Method | I4: Receipt No | J4: Bank/Account | K4: Notes | L4: Penalty
A5: 1 | B5: 1st Semester | C5: Hall Fee | D5: 2500 | E5: 2024-02-01 | F5: 2024-01-28 | G5: Paid | H5: Bank | I5: RCP-1000 | L5: 0
A6: 2 | B6: 1st Semester | C6: Faculty Fee | D6: 3000 | E6: 2024-02-01 | F6: 2024-01-28 | G6: Paid | H6: Bank | I6: RCP-1001 | L6: 0
A7: 3 | B7: 1st Semester | C7: Library Fee | D7: 500 | E7: 2024-02-01 | F7: 2024-01-28 | G7: Paid | H7: Bank | I7: RCP-1002 | L7: 0
A8: 4 | B8: 2nd Semester | C8: Hall Fee | D8: 2500 | E8: 2024-08-01 | F8: 2024-07-30 | G8: Paid | H8: Bank | I8: RCP-1003 | L8: 0
A9: 5 | B9: 2nd Semester | C9: Faculty Fee | D9: 3000 | E9: 2024-08-01 | F9: 2024-07-30 | G9: Paid | H9: Bank | I9: RCP-1004 | L9: 0
A10: 6 | B10: 3rd Semester | C10: Hall Fee | D10: 2500 | E10: 2025-02-01 | G10: Pending | L10: 0
A11: 7 | B11: 3rd Semester | C11: Faculty Fee | D11: 3200 | E11: 2025-02-01 | G11: Pending | L11: 0
A13: TOTAL FEES | D13: =SUM(D5:D11)
A14: PAID | D14: =SUMIF(G5:G11,"Paid",D5:D11)
A15: DUE / PENDING | D15: =SUMIF(G5:G11,"Pending",D5:D11)

Sheet 👤 My Details
A1: 👤 STUDENT PROFILE
A3: Full Name: | D3: SHOVON
A4: Student ID: | D4: 20XXXXXXX
A5: Registration No: | D5: 2020-XXXXX
A6: Session: | D6: 2020-21
A7: Department: | D7: CSE
A8: Faculty: | D8: Engineering
A9: University: | D9: My University
A10: Semester: | D10: 3rd Semester
A11: Email: | D11: shovon@email.com
A12: Phone: | D12: +880-XXXXXXXXX
A13: Hall/Hostel: | D13: Hall Name
A14: Advisor: | D14: Dr. Someone
A15: Date of Birth:
A16: Blood Group: | D16: B+
A17: Address:
